[{
	"fileName": "1.jpg",
	"title": "mashroom",
	"desc": "mashroom"
}, {
	"fileName": "2.jpg",
	"title": "maple",
	"desc": "maple"
}, {
	"fileName": "3.jpg",
	"title": "red flower",
	"desc": "red flower"
}, {
	"fileName": "4.jpg",
	"title": "web",
	"desc": "web"
}, {
	"fileName": "5.jpg",
	"title": "blue flower",
	"desc": "blue flower"
}, {
	"fileName": "6.jpg",
	"title": "white flower",
	"desc": "white flower"
}, {
	"fileName": "7.jpg",
	"title": "leaf",
	"desc": "leaf"
}, {
	"fileName": "8.jpg",
	"title": "red fruit",
	"desc": "red fruit"
}, {
	"fileName": "9.jpg",
	"title": "purple flower",
	"desc": "purple flower"
}, {
	"fileName": "10.jpg",
	"title": "yellow flower",
	"desc": "yellow flower"
}]